progressbox/__init__.py
progressbox/__version__.py
progressbox/compat.py
progressbox/config.py
progressbox/core.py
progressbox/events.py
progressbox/metrics.py
progressbox/py.typed
progressbox/state.py
progressbox/adapters/__init__.py
progressbox/adapters/joblib_.py
progressbox/ipc/__init__.py
progressbox/ipc/manager.py
progressbox/ipc/queue.py
progressbox/ipc/reporter.py
progressbox/render/__init__.py
progressbox/render/ascii.py
progressbox/render/base.py
progressbox/render/jupyter.py
progressbox/render/string_.py
progressbox/utils/__init__.py
progressbox/utils/formatting.py
progressbox/utils/terminal.py
progressbox/utils/width.py
progressbox-0.1.0.dist-info/licenses/LICENSE
progressbox-0.1.0.dist-info/METADATA
progressbox-0.1.0.dist-info/WHEEL
progressbox-0.1.0.dist-info/top_level.txt
progressbox-0.1.0.dist-info/RECORD
