Metadata-Version: 2.4
Name: progressbox
Version: 0.1.0
Summary: Stage-aware progress monitoring for parallel Python jobs
Author-email: Zaafir Hasan <zaafirfhasan@gmail.com>
License: MIT
Keywords: progress,parallel,monitoring,multiprocessing,joblib
Classifier: Development Status :: 3 - Alpha
Classifier: Intended Audience :: Developers
Classifier: Intended Audience :: Science/Research
Classifier: License :: OSI Approved :: MIT License
Classifier: Programming Language :: Python :: 3
Classifier: Programming Language :: Python :: 3.9
Classifier: Programming Language :: Python :: 3.10
Classifier: Programming Language :: Python :: 3.11
Classifier: Programming Language :: Python :: 3.12
Classifier: Topic :: Software Development :: Libraries
Classifier: Topic :: System :: Monitoring
Requires-Python: >=3.9
License-File: LICENSE
Requires-Dist: wcwidth>=0.2.5
Provides-Extra: rich
Requires-Dist: rich>=12.0.0; extra == "rich"
Provides-Extra: perf
Requires-Dist: orjson>=3.8.0; extra == "perf"
Provides-Extra: dev
Requires-Dist: pytest>=7.0; extra == "dev"
Requires-Dist: pytest-cov>=4.0; extra == "dev"
Requires-Dist: black>=22.0; extra == "dev"
Requires-Dist: ruff>=0.1.0; extra == "dev"
Requires-Dist: mypy>=1.0; extra == "dev"
Requires-Dist: ipython; extra == "dev"
Dynamic: license-file
